kilu/__init__.py
kilu/dir2kilu.py
kilu-1.1.dist-info/LICENSE
kilu-1.1.dist-info/METADATA
kilu-1.1.dist-info/WHEEL
kilu-1.1.dist-info/entry_points.txt
kilu-1.1.dist-info/top_level.txt
kilu-1.1.dist-info/RECORD
