Metadata-Version: 2.1
Name: kilu
Version: 1.1
Summary: Kilu: A YAML-based template system for generating project files
Home-page: https://github.com/buanzo/kilu
Author: Arturo "Buanzo" Busleiman
Author-email: buanzo@buanzo.com.ar
Classifier: Development Status :: 4 - Beta
Classifier: Intended Audience :: Developers
Classifier: License :: OSI Approved :: MIT License
Classifier: Operating System :: OS Independent
Classifier: Programming Language :: Python
Classifier: Programming Language :: Python :: 3
Classifier: Programming Language :: Python :: 3.6
Classifier: Programming Language :: Python :: 3.7
Classifier: Programming Language :: Python :: 3.8
Classifier: Programming Language :: Python :: 3.9
License-File: LICENSE
Requires-Dist: PyYAML
